Design/dual_clock_async_fifo_design.v
// ============================================================================
// Module: Dual-Clock Asynchronous FIFO
// File: dual_clock_async_fifo_design.v
// ============================================================================
// Description:
//   This module implements a fully synchronous dual-clock asynchronous FIFO 
//   (First-In-First-Out) buffer that allows data transfer between two 
//   independent clock domains. The design uses Gray code pointers to safely 
//   cross clock domains and prevent metastability issues.
//
// Architecture:
//   - Memory array: 16 locations × 8 bits (configurable via parameters)
//   - Write clock domain (wclk): Handles write operations and full flag
//   - Read clock domain (rclk): Handles read operations and empty flag
//   - Pointer synchronization: 2-stage synchronizers for safe CDC
//   - Gray code encoding: Ensures only one bit changes during pointer updates
//
// Key Features:
//   • Asynchronous read, synchronous write memory architecture
//   • Full and empty flags generated in respective clock domains
//   • Active-low asynchronous reset for both clock domains
//   • Parameterizable data width (DSIZE) and address width (ASIZE)
//   • Safe clock domain crossing using Gray code pointers
//   • No data loss under normal operating conditions
//
// Parameters:
//   DSIZE - Data width in bits (default: 8)
//   ASIZE - Address width in bits (default: 4, giving 2^4 = 16 depth)
//
// Ports:
//   Output:
//     rdata[7:0]  - Read data output (asynchronous to rclk)
//     wfull       - Write full flag (synchronized to wclk)
//                   When high, FIFO is full; writes should be inhibited
//     rempty      - Read empty flag (synchronized to rclk)
//                   When high, FIFO is empty; reads should be inhibited
//   
//   Input:
//     wdata[7:0]  - Write data input
//     winc        - Write increment enable (active high)
//                   When asserted and !wfull, data is written to FIFO
//     wclk        - Write clock domain
//     wrst_n      - Write domain asynchronous reset (active low)
//     rinc        - Read increment enable (active high)
//                   When asserted and !rempty, data is read from FIFO
//     rclk        - Read clock domain (independent of wclk)
//     rrst_n      - Read domain asynchronous reset (active low)
//
// Operation:
//   1. Write Operation:
//      - When winc=1 and wfull=0, data on wdata is written to memory
//      - Write pointer increments and converts to Gray code
//      - Gray-coded pointer synchronized to read clock domain
//   
//   2. Read Operation:
//      - When rinc=1 and rempty=0, data appears on rdata
//      - Read pointer increments and converts to Gray code
//      - Gray-coded pointer synchronized to write clock domain
//   
//   3. Full/Empty Detection:
//      - Empty: Read Gray pointer equals synchronized write pointer
//      - Full: Write Gray pointer equals inverted MSBs of sync'd read pointer
//
// Design Notes:
//   - Both clock domains must have resets asserted simultaneously for 
//     proper initialization, though they can be released asynchronously
//   - Maximum throughput is one word per clock cycle in each domain
//   - Gray code ensures safe CDC by allowing only single-bit transitions
//   - Two flip-flop synchronizers provide adequate MTBF for most applications
//
// Author: [Your Name]
// Date: [Date]
// Version: 1.0
// ============================================================================

module fifo1 (
  output [7:0] rdata,
  output       wfull,
  output       rempty,
  input  [7:0] wdata,
  input        winc,
  input        wclk,
  input        wrst_n,
  input        rinc,
  input        rclk,
  input        rrst_n
);

parameter DSIZE = 8;
parameter ASIZE = 4;

wire [ASIZE-1:0] waddr, raddr;
wire [ASIZE:0] wptr, rptr, wrptr2, rwptr2;

sync_r2w #(ASIZE) sync_r2w_inst (
  .wrptr2(wrptr2),
  .rptr(rptr),
  .wclk(wclk),
  .wrst_n(wrst_n)
);

sync_w2r #(ASIZE) sync_w2r_inst (
  .rwptr2(rwptr2),
  .wptr(wptr),
  .rclk(rclk),
  .rrst_n(rrst_n)
);

fifomem #(DSIZE, ASIZE) fifomem_inst (
  .rdata(rdata),
  .wdata(wdata),
  .waddr(waddr),
  .raddr(raddr),
  .wclken(winc),
  .wfull_n(!wfull),
  .wclk(wclk)
);

rptr_empty #(ASIZE) rptr_empty_inst (
  .rempty(rempty),
  .raddr(raddr),
  .rptr(rptr),
  .rwptr2(rwptr2),
  .rinc(rinc),
  .rclk(rclk),
  .rrst_n(rrst_n)
);

wptr_full #(ASIZE) wptr_full_inst (
  .wfull(wfull),
  .waddr(waddr),
  .wptr(wptr),
  .wrptr2(wrptr2),
  .winc(winc),
  .wclk(wclk),
  .wrst_n(wrst_n)
);

endmodule

// ============================================================================
// Module: Read Pointer and Empty Flag Generator
// ============================================================================
// Description:
//   Generates the read pointer in Gray code format and the empty flag for
//   the asynchronous FIFO. The read pointer is incremented when rinc is
//   asserted and the FIFO is not empty.
//
// Architecture:
//   - Maintains binary pointer (rbin) for address generation
//   - Converts binary to Gray code for safe clock domain crossing
//   - Compares synchronized write pointer with current read pointer
//   - Generates empty flag when pointers match
//
// Parameters:
//   ADDRSIZE - Address width in bits (default: 4)
//              Determines FIFO depth as 2^ADDRSIZE
//
// Ports:
//   Output:
//     rempty            - Empty flag (active high, synchronized to rclk)
//                         High when FIFO is empty, no valid data to read
//     raddr[ADDRSIZE-1:0] - Memory read address (binary, MSB excluded)
//     rptr[ADDRSIZE:0]    - Read pointer in Gray code format
//   
//   Input:
//     rwptr2[ADDRSIZE:0]  - Synchronized write pointer from write clock domain
//     rinc                - Read increment enable (active high)
//     rclk                - Read clock domain
//     rrst_n              - Asynchronous reset (active low)
//
// Operation:
//   1. Binary pointer increments when rinc=1 and !rempty
//   2. Binary pointer converted to Gray code: G = (B>>1) ^ B
//   3. Gray-coded pointer sent to write domain via synchronizer
//   4. Empty detected when local Gray pointer equals synced write pointer
//
// Design Notes:
//   - Uses ADDRSIZE+1 bits for pointer to distinguish full vs empty
//   - MSB of raddr excludes the extra pointer bit
//   - Empty flag registered for clean timing
// ============================================================================
module rptr_empty #(
  parameter ADDRSIZE = 4
) (
  output reg              rempty,
  output [ADDRSIZE-1:0]   raddr,
  output reg [ADDRSIZE:0] rptr,
  input  [ADDRSIZE:0]     rwptr2,
  input                   rinc,
  input                   rclk,
  input                   rrst_n
);

reg [ADDRSIZE:0] rbin;
wire [ADDRSIZE:0] rgnext, rbnext;

// Memory read-address pointer
assign raddr = rbin[ADDRSIZE-1:0];

// Generate next binary and Gray values
assign rbnext = rbin + (rinc & ~rempty);
assign rgnext = (rbnext >> 1) ^ rbnext;

// Update pointers - use current pointer for comparison, not next
always @(posedge rclk or negedge rrst_n) begin
  if (!rrst_n) begin
    rbin <= {(ADDRSIZE+1){1'b0}};
    rptr <= {(ADDRSIZE+1){1'b0}};
  end else begin
    rbin <= rbnext;
    rptr <= rgnext;
  end
end

// Empty detection - compare current Gray pointer with synchronized write pointer
wire rempty_val;
assign rempty_val = (rptr == rwptr2);

always @(posedge rclk or negedge rrst_n) begin
  if (!rrst_n)
    rempty <= 1'b1;
  else
    rempty <= rempty_val;
end

endmodule

// ============================================================================
// Module: Read-to-Write Clock Domain Synchronizer
// ============================================================================
// Description:
//   Two-stage synchronizer that safely transfers the read pointer (in Gray
//   code) from the read clock domain to the write clock domain. This is
//   critical for full flag generation in the write domain.
//
// Architecture:
//   - Uses two flip-flops in series for metastability resolution
//   - Input is Gray-coded pointer ensuring single-bit transitions
//   - Single-bit changes guarantee safe synchronization even if sampled
//     during metastable event
//
// Parameters:
//   ADDRSIZE - Address width in bits (default: 4)
//              Pointer width is ADDRSIZE+1 bits
//
// Ports:
//   Output:
//     wrptr2[ADDRSIZE:0] - Synchronized read pointer in write clock domain
//                          (2nd stage of synchronizer)
//   
//   Input:
//     rptr[ADDRSIZE:0]   - Read pointer in Gray code from read domain
//     wclk               - Write clock domain
//     wrst_n             - Asynchronous reset (active low)
//
// Operation:
//   1. On each wclk edge, rptr is sampled into wrptr1 (1st stage)
//   2. On next wclk edge, wrptr1 is transferred to wrptr2 (2nd stage)
//   3. wrptr2 is used by write domain for full flag comparison
//
// Design Notes:
//   - CRITICAL: Input must be Gray-coded to ensure only one bit changes
//   - Two stages provide adequate MTBF for most practical applications
//   - Reset must be asynchronous to handle power-up conditions
//   - For higher reliability requirements, consider 3+ stage synchronizers
// ============================================================================
module sync_r2w #(
  parameter ADDRSIZE = 4
) (
  output reg [ADDRSIZE:0] wrptr2,
  input  [ADDRSIZE:0]     rptr,
  input                   wclk,
  input                   wrst_n
);

reg [ADDRSIZE:0] wrptr1;

always @(posedge wclk or negedge wrst_n) begin
  if (!wrst_n) begin
    wrptr2 <= {(ADDRSIZE+1){1'b0}};
    wrptr1 <= {(ADDRSIZE+1){1'b0}};
  end else begin
    wrptr1 <= rptr;
    wrptr2 <= wrptr1;
  end
end

endmodule

// ============================================================================
// Module: Write-to-Read Clock Domain Synchronizer
// ============================================================================
// Description:
//   Two-stage synchronizer that safely transfers the write pointer (in Gray
//   code) from the write clock domain to the read clock domain. This is
//   critical for empty flag generation in the read domain.
//
// Architecture:
//   - Uses two flip-flops in series for metastability resolution
//   - Input is Gray-coded pointer ensuring single-bit transitions
//   - Single-bit changes guarantee safe synchronization even if sampled
//     during metastable event
//
// Parameters:
//   ADDRSIZE - Address width in bits (default: 4)
//              Pointer width is ADDRSIZE+1 bits
//
// Ports:
//   Output:
//     rwptr2[ADDRSIZE:0] - Synchronized write pointer in read clock domain
//                          (2nd stage of synchronizer)
//   
//   Input:
//     wptr[ADDRSIZE:0]   - Write pointer in Gray code from write domain
//     rclk               - Read clock domain
//     rrst_n             - Asynchronous reset (active low)
//
// Operation:
//   1. On each rclk edge, wptr is sampled into rwptr1 (1st stage)
//   2. On next rclk edge, rwptr1 is transferred to rwptr2 (2nd stage)
//   3. rwptr2 is used by read domain for empty flag comparison
//
// Design Notes:
//   - CRITICAL: Input must be Gray-coded to ensure only one bit changes
//   - Two stages provide adequate MTBF for most practical applications
//   - Reset must be asynchronous to handle power-up conditions
//   - For higher reliability requirements, consider 3+ stage synchronizers
// ============================================================================
module sync_w2r #(
  parameter ADDRSIZE = 4
) (
  output reg [ADDRSIZE:0] rwptr2,
  input  [ADDRSIZE:0]     wptr,
  input                   rclk,
  input                   rrst_n
);

reg [ADDRSIZE:0] rwptr1;

always @(posedge rclk or negedge rrst_n) begin
  if (!rrst_n) begin
    rwptr2 <= {(ADDRSIZE+1){1'b0}};
    rwptr1 <= {(ADDRSIZE+1){1'b0}};
  end else begin
    rwptr1 <= wptr;
    rwptr2 <= rwptr1;
  end
end

endmodule

// ============================================================================
// Module: Write Pointer and Full Flag Generator
// ============================================================================
// Description:
//   Generates the write pointer in Gray code format and the full flag for
//   the asynchronous FIFO. The write pointer is incremented when winc is
//   asserted and the FIFO is not full.
//
// Architecture:
//   - Maintains binary pointer (wbin) for address generation
//   - Converts binary to Gray code for safe clock domain crossing
//   - Compares synchronized read pointer with current write pointer
//   - Generates full flag when pointers match with MSB inversion
//
// Parameters:
//   ADDRSIZE - Address width in bits (default: 4)
//              Determines FIFO depth as 2^ADDRSIZE
//
// Ports:
//   Output:
//     wfull             - Full flag (active high, synchronized to wclk)
//                         High when FIFO is full, writes should be inhibited
//     waddr[ADDRSIZE-1:0] - Memory write address (binary, MSB excluded)
//     wptr[ADDRSIZE:0]    - Write pointer in Gray code format
//   
//   Input:
//     wrptr2[ADDRSIZE:0]  - Synchronized read pointer from read clock domain
//     winc                - Write increment enable (active high)
//     wclk                - Write clock domain
//     wrst_n              - Asynchronous reset (active low)
//
// Operation:
//   1. Binary pointer increments when winc=1 and !wfull
//   2. Binary pointer converted to Gray code: G = (B>>1) ^ B
//   3. Gray-coded pointer sent to read domain via synchronizer
//   4. Full detected when: wptr[MSB:MSB-1] == ~rwptr[MSB:MSB-1] AND
//                          wptr[MSB-2:0] == rwptr[MSB-2:0]
//
// Full Detection Logic:
//   - For a FIFO of depth 2^n, the full condition occurs when:
//     * The two MSBs of write pointer are opposite of read pointer's MSBs
//     * All remaining lower bits are equal
//   - This distinguishes "full" from "empty" condition using extra pointer bit
//
// Design Notes:
//   - Uses ADDRSIZE+1 bits for pointer to distinguish full vs empty
//   - MSB of waddr excludes the extra pointer bit
//   - Full flag registered for clean timing
// ============================================================================
module wptr_full #(
  parameter ADDRSIZE = 4
) (
  output reg              wfull,
  output [ADDRSIZE-1:0]   waddr,
  output reg [ADDRSIZE:0] wptr,
  input  [ADDRSIZE:0]     wrptr2,
  input                   winc,
  input                   wclk,
  input                   wrst_n
);

reg [ADDRSIZE:0] wbin;
wire [ADDRSIZE:0] wgnext, wbnext;

// Memory write-address pointer
assign waddr = wbin[ADDRSIZE-1:0];

// Generate next binary and Gray values
// Fix: Use direct increment without conditional
assign wbnext = wbin + 1'b1;
assign wgnext = (wbnext >> 1) ^ wbnext;

// Update pointers - use current pointer for comparison, not next
always @(posedge wclk or negedge wrst_n) begin
  if (!wrst_n) begin
    wbin <= {(ADDRSIZE+1){1'b0}};
    wptr <= {(ADDRSIZE+1){1'b0}};
  end else if (winc & ~wfull) begin
    wbin <= wbnext;
    wptr <= wgnext;
  end
end

// Full detection - compare current Gray pointer with synchronized read pointer
wire wfull_val;
assign wfull_val = (wptr == {~wrptr2[ADDRSIZE:ADDRSIZE-1], wrptr2[ADDRSIZE-2:0]});

always @(posedge wclk or negedge wrst_n) begin
  if (!wrst_n)
    wfull <= 1'b0;
  else if (winc & ~wfull)
    wfull <= wfull_val;
end

endmodule

// ============================================================================
// Module: FIFO Memory Array
// ============================================================================
// Description:
//   Implements the storage array for the asynchronous FIFO with synchronous
//   write and asynchronous read operations. This is a standard implementation
//   for dual-clock FIFOs where read data appears combinationally.
//
// Architecture:
//   - Single-port memory array with synchronous writes
//   - Asynchronous (combinational) reads
//   - Write enable controlled by wclken and wfull_n signals
//
// Parameters:
//   DATASIZE - Data width in bits (default: 8)
//   ADDRSIZE - Address width in bits (default: 4)
//              Memory depth = 2^ADDRSIZE locations
//
// Ports:
//   Output:
//     rdata[DATASIZE-1:0] - Read data output (asynchronous)
//                           Changes immediately when raddr changes
//   
//   Input:
//     wdata[DATASIZE-1:0] - Write data input
//     waddr[ADDRSIZE-1:0] - Write address input
//     raddr[ADDRSIZE-1:0] - Read address input
//     wclken              - Write clock enable (active high)
//                           When high with wfull_n, write occurs on wclk edge
//     wfull_n             - Write full flag (active low)
//                           Prevents writes when FIFO is full
//     wclk                - Write clock domain
//
// Operation:
//   - Write: On posedge wclk, if wclken && wfull_n, MEM[waddr] <= wdata
//   - Read:  Continuously drives rdata = MEM[raddr] (asynchronous)
//
// Design Notes:
//   - Asynchronous read means rdata changes as soon as raddr changes
//   - This is acceptable for FIFO operation since raddr only changes on rclk
//   - For synchronous read applications, consider adding output register
//   - Memory depth is 2^ADDRSIZE (e.g., ASIZE=4 gives 16 locations)
//   - No initialization specified; simulation starts with unknown values
// ============================================================================
module fifomem #(
  parameter DATASIZE = 8,
  parameter ADDRSIZE = 4
) (
  output [DATASIZE-1:0] rdata,
  input  [DATASIZE-1:0] wdata,
  input  [ADDRSIZE-1:0] waddr,
  input  [ADDRSIZE-1:0] raddr,
  input                 wclken,
  input                 wfull_n,
  input                 wclk
);

localparam DEPTH = 1 << ADDRSIZE;

// Memory array
reg [DATASIZE-1:0] MEM [0:DEPTH-1];

// Asynchronous read
assign rdata = MEM[raddr];

// Synchronous write
always @(posedge wclk) begin
  if (wclken && wfull_n) begin
    MEM[waddr] <= wdata;
  end
end

endmodule

Testbench/tb_fifo_wave.v
// Waveform testbench for FIFO debugging
`timescale 1ns/1ps

module tb_fifo_wave;

localparam DSIZE = 8;
localparam ASIZE = 4;
localparam WCLK_PERIOD = 20;
localparam RCLK_PERIOD = 30;

reg [DSIZE-1:0] wdata;
reg             winc;
reg             wclk;
reg             wrst_n;
reg             rinc;
reg             rclk;
reg             rrst_n;

wire [DSIZE-1:0] rdata;
wire             wfull;
wire             rempty;

fifo1 uut (
  .rdata(rdata),
  .wfull(wfull),
  .rempty(rempty),
  .wdata(wdata),
  .winc(winc),
  .wclk(wclk),
  .wrst_n(wrst_n),
  .rinc(rinc),
  .rclk(rclk),
  .rrst_n(rrst_n)
);

initial begin
  wclk = 0;
  forever #(WCLK_PERIOD/2) wclk = ~wclk;
end

initial begin
  rclk = 0;
  forever #(RCLK_PERIOD/2) rclk = ~rclk;
end

initial begin
  $dumpfile("fifo_waveform.vcd");
  $dumpvars(0, tb_fifo_wave);
  
  wdata = 0; winc = 0; wrst_n = 0; rinc = 0; rrst_n = 0;
  #20;
  wrst_n = 1; rrst_n = 1;
  #50;
  
  // Write exactly 16 items
  repeat (16) begin
    @(posedge wclk);
    wdata = wdata + 1;
    winc = 1;
    #1;
    winc = 0;
  end
  
  #200;
  
  // Read all items
  repeat (16) begin
    @(posedge rclk);
    rinc = 1;
    #1;
    rinc = 0;
  end
  
  #100;
  $finish;
end

endmodule

fifo_waveform.vcd
$date
	Thu Aug 27 09:40:57 2026
$end
$version
	Icarus Verilog
$end
$timescale
	1ps
$end
$scope module tb_fifo_wave $end
$var wire 1 ! wfull $end
$var wire 1 " rempty $end
$var wire 8 # rdata [7:0] $end
$var reg 1 $ rclk $end
$var reg 1 % rinc $end
$var reg 1 & rrst_n $end
$var reg 1 ' wclk $end
$var reg 8 ( wdata [7:0] $end
$var reg 1 ) winc $end
$var reg 1 * wrst_n $end
$scope module uut $end
$var wire 1 $ rclk $end
$var wire 1 % rinc $end
$var wire 1 & rrst_n $end
$var wire 1 ' wclk $end
$var wire 8 + wdata [7:0] $end
$var wire 1 ) winc $end
$var wire 1 * wrst_n $end
$var wire 5 , wrptr2 [4:0] $end
$var wire 5 - wptr [4:0] $end
$var wire 1 ! wfull $end
$var wire 4 . waddr [3:0] $end
$var wire 5 / rwptr2 [4:0] $end
$var wire 5 0 rptr [4:0] $end
$var wire 1 " rempty $end
$var wire 8 1 rdata [7:0] $end
$var wire 4 2 raddr [3:0] $end
$scope module fifomem_inst $end
$var wire 8 3 rdata [7:0] $end
$var wire 1 ' wclk $end
$var wire 1 ) wclken $end
$var wire 8 4 wdata [7:0] $end
$var wire 1 5 wfull_n $end
$var wire 4 6 waddr [3:0] $end
$var wire 4 7 raddr [3:0] $end
$upscope $end
$scope module rptr_empty_inst $end
$var wire 1 $ rclk $end
$var wire 5 8 rgnext [4:0] $end
$var wire 1 % rinc $end
$var wire 1 & rrst_n $end
$var wire 5 9 rwptr2 [4:0] $end
$var wire 1 : rempty_val $end
$var wire 5 ; rbnext [4:0] $end
$var wire 4 < raddr [3:0] $end
$var reg 5 = rbin [4:0] $end
$var reg 1 " rempty $end
$var reg 5 > rptr [4:0] $end
$upscope $end
$scope module sync_r2w_inst $end
$var wire 5 ? rptr [4:0] $end
$var wire 1 ' wclk $end
$var wire 1 * wrst_n $end
$var reg 5 @ wrptr1 [4:0] $end
$var reg 5 A wrptr2 [4:0] $end
$upscope $end
$scope module sync_w2r_inst $end
$var wire 1 $ rclk $end
$var wire 1 & rrst_n $end
$var wire 5 B wptr [4:0] $end
$var reg 5 C rwptr1 [4:0] $end
$var reg 5 D rwptr2 [4:0] $end
$upscope $end
$scope module wptr_full_inst $end
$var wire 1 ' wclk $end
$var wire 5 E wgnext [4:0] $end
$var wire 1 ) winc $end
$var wire 5 F wrptr2 [4:0] $end
$var wire 1 * wrst_n $end
$var wire 1 G wfull_val $end
$var wire 5 H wbnext [4:0] $end
$var wire 4 I waddr [3:0] $end
$var reg 5 J wbin [4:0] $end
$var reg 1 ! wfull $end
$var reg 5 K wptr [4:0] $end
$upscope $end
$upscope $end
$upscope $end
$enddefinitions $end
#0
$dumpvars
b0 K
b0 J
b0 I
b0 H
0G
b0 F
b0 E
b0 D
b0 C
b0 B
b0 A
b0 @
b0 ?
b0 >
b0 =
b0 <
b0 ;
1:
b0 9
b0 8
b0 7
b0 6
15
b0 4
bx 3
b0 2
bx 1
b0 0
b0 /
b0 .
b0 -
b0 ,
b0 +
0*
0)
b0 (
0'
0&
0%
0$
bx #
1"
0!
$end
#10000
1'
#15000
1$
#20000
0'
1&
1*
#30000
1'
0$
#40000
0'
#45000
1$
#50000
1'
#60000
0'
0$
#70000
b1 #
b1 1
b1 3
b1 E
b1 H
1)
b1 (
b1 +
b1 4
1'
#71000
b0 E
b0 H
0)
#75000
1$
#80000
0'
#90000
b10 #
b10 1
b10 3
b1 E
b1 H
1)
b10 (
b10 +
b10 4
1'
0$
#91000
b0 E
b0 H
0)
#100000
0'
#105000
1$
#110000
b11 #
b11 1
b11 3
b1 E
b1 H
1)
b11 (
b11 +
b11 4
1'
#111000
b0 E
b0 H
0)
#120000
0'
0$
#130000
b100 #
b100 1
b100 3
b1 E
b1 H
1)
b100 (
b100 +
b100 4
1'
#131000
b0 E
b0 H
0)
#135000
1$
#140000
0'
#150000
b101 #
b101 1
b101 3
b1 E
b1 H
1)
b101 (
b101 +
b101 4
1'
0$
#151000
b0 E
b0 H
0)
#160000
0'
#165000
1$
#170000
b110 #
b110 1
b110 3
b1 E
b1 H
1)
b110 (
b110 +
b110 4
1'
#171000
b0 E
b0 H
0)
#180000
0'
0$
#190000
b111 #
b111 1
b111 3
b1 E
b1 H
1)
b111 (
b111 +
b111 4
1'
#191000
b0 E
b0 H
0)
#195000
1$
#200000
0'
#210000
b1000 #
b1000 1
b1000 3
b1 E
b1 H
1)
b1000 (
b1000 +
b1000 4
1'
0$
#211000
b0 E
b0 H
0)
#220000
0'
#225000
1$
#230000
b1001 #
b1001 1
b1001 3
b1 E
b1 H
1)
b1001 (
b1001 +
b1001 4
1'
#231000
b0 E
b0 H
0)
#240000
0'
0$
#250000
b1010 #
b1010 1
b1010 3
b1 E
b1 H
1)
b1010 (
b1010 +
b1010 4
1'
#251000
b0 E
b0 H
0)
#255000
1$
#260000
0'
#270000
b1011 #
b1011 1
b1011 3
b1 E
b1 H
1)
b1011 (
b1011 +
b1011 4
1'
0$
#271000
b0 E
b0 H
0)
#280000
0'
#285000
1$
#290000
b1100 #
b1100 1
b1100 3
b1 E
b1 H
1)
b1100 (
b1100 +
b1100 4
1'
#291000
b0 E
b0 H
0)
#300000
0'
0$
#310000
b1101 #
b1101 1
b1101 3
b1 E
b1 H
1)
b1101 (
b1101 +
b1101 4
1'
#311000
b0 E
b0 H
0)
#315000
1$
#320000
0'
#330000
b1110 #
b1110 1
b1110 3
b1 E
b1 H
1)
b1110 (
b1110 +
b1110 4
1'
0$
#331000
b0 E
b0 H
0)
#340000
0'
#345000
1$
#350000
b1111 #
b1111 1
b1111 3
b1 E
b1 H
1)
b1111 (
b1111 +
b1111 4
1'
#351000
b0 E
b0 H
0)
#360000
0'
0$
#370000
b10000 #
b10000 1
b10000 3
b1 E
b1 H
1)
b10000 (
b10000 +
b10000 4
1'
#371000
b0 E
b0 H
0)
#375000
1$
#380000
0'
#390000
1'
0$
#400000
0'
#405000
1$
#410000
1'
#420000
0'
0$
#430000
1'
#435000
1$
#440000
0'
#450000
1'
0$
#460000
0'
#465000
1$
#470000
1'
#480000
0'
0$
#490000
1'
#495000
1$
#500000
0'
#510000
1'
0$
#520000
0'
#525000
1$
#530000
1'
#540000
0'
0$
#550000
1'
#555000
1$
#560000
0'
#570000
1'
0$
#580000
0'
#585000
1%
1$
#586000
0%
#590000
1'
#600000
0'
0$
#610000
1'
#615000
1%
1$
#616000
0%
#620000
0'
#630000
1'
0$
#640000
0'
#645000
1%
1$
#646000
0%
#650000
1'
#660000
0'
0$
#670000
1'
#675000
1%
1$
#676000
0%
#680000
0'
#690000
1'
0$
#700000
0'
#705000
1%
1$
#706000
0%
#710000
1'
#720000
0'
0$
#730000
1'
#735000
1%
1$
#736000
0%
#740000
0'
#750000
1'
0$
#760000
0'
#765000
1%
1$
#766000
0%
#770000
1'
#780000
0'
0$
#790000
1'
#795000
1%
1$
#796000
0%
#800000
0'
#810000
1'
0$
#820000
0'
#825000
1%
1$
#826000
0%
#830000
1'
#840000
0'
0$
#850000
1'
#855000
1%
1$
#856000
0%
#860000
0'
#870000
1'
0$
#880000
0'
#885000
1%
1$
#886000
0%
#890000
1'
#900000
0'
0$
#910000
1'
#915000
1%
1$
#916000
0%
#920000
0'
#930000
1'
0$
#940000
0'
#945000
1%
1$
#946000
0%
#950000
1'
#960000
0'
0$
#970000
1'
#975000
1%
1$
#976000
0%
#980000
0'
#990000
1'
0$
#1000000
0'
#1005000
1%
1$
#1006000
0%
#1010000
1'
#1020000
0'
0$
#1030000
1'
#1035000
1%
1$
#1036000
0%
